LICENSE
MANIFEST.in
README.md
pyproject.toml
setup.cfg
setup.py
csv_generator/__init__.py
csv_generator/admin.py
csv_generator/apps.py
csv_generator/generator.py
csv_generator/models.py
csv_generator/tests.py
csv_generator/views.py
csv_generator/locale/pl/LC_MESSAGES/django.mo
csv_generator/locale/pl/LC_MESSAGES/django.po
csv_generator/migrations/__init__.py
dj_csv_generator.egg-info/PKG-INFO
dj_csv_generator.egg-info/SOURCES.txt
dj_csv_generator.egg-info/dependency_links.txt
dj_csv_generator.egg-info/requires.txt
dj_csv_generator.egg-info/top_level.txt